{
  "source_file": "Task2.pdf",
  "source_type": "same_pdf",
  "exam_title": "MNF130 - Oppgaver uke 6: Questions with correct answers",
  "course_code": "MNF130",
  "solutions": [
    {
      "question_id": "q1",
      "question_number": "1",
      "solution_text": "Let P(x) be the statement “The word x contains the letter a”. What are these truth values?",
      "page_start": 1,
      "page_end": 1,
      "subsolutions": [
        {
          "question_id": "q1a",
          "label": "a",
          "answer": "True. The word “orange” contains the letter a.",
          "explanation": null,
          "grading_points": [],
          "points": null,
          "page_start": 1,
          "page_end": 1,
          "source": "same_pdf"
        },
        {
          "question_id": "q1b",
          "label": "b",
          "answer": "False. The word “lemon” does not contain the letter a.",
          "explanation": null,
          "grading_points": [],
          "points": null,
          "page_start": 1,
          "page_end": 1,
          "source": "same_pdf"
        },
        {
          "question_id": "q1c",
          "label": "c",
          "answer": "False. The word “true” does not contain the letter a.",
          "explanation": null,
          "grading_points": [],
          "points": null,
          "page_start": 1,
          "page_end": 1,
          "source": "same_pdf"
        },
        {
          "question_id": "q1d",
          "label": "d",
          "answer": "True. The word “false” contains the letter a.",
          "explanation": null,
          "grading_points": [],
          "points": null,
          "page_start": 1,
          "page_end": 1,
          "source": "same_pdf"
        }
      ],
      "warnings": []
    },
    {
      "question_id": "q2",
      "question_number": "2",
      "solution_text": "Translate these statements into English, where C(x) is “x is a comedian” and F(x) is “x is funny” and the domain consists of all people.",
      "page_start": 1,
      "page_end": 1,
      "subsolutions": [
        {
          "question_id": "q2a",
          "label": "a",
          "answer": "Every comedian is funny.",
          "explanation": null,
          "grading_points": [],
          "points": null,
          "page_start": 1,
          "page_end": 1,
          "source": "same_pdf"
        },
        {
          "question_id": "q2b",
          "label": "b",
          "answer": "Every person is a comedian and is funny.",
          "explanation": null,
          "grading_points": [],
          "points": null,
          "page_start": 1,
          "page_end": 1,
          "source": "same_pdf"
        },
        {
          "question_id": "q2c",
          "label": "c",
          "answer": "There is at least one person such that if that person is a comedian, then that person is funny.",
          "explanation": null,
          "grading_points": [],
          "points": null,
          "page_start": 1,
          "page_end": 1,
          "source": "same_pdf"
        },
        {
          "question_id": "q2d",
          "label": "d",
          "answer": "There is at least one person who is both a comedian and funny.",
          "explanation": null,
          "grading_points": [],
          "points": null,
          "page_start": 1,
          "page_end": 1,
          "source": "same_pdf"
        }
      ],
      "warnings": []
    },
    {
      "question_id": "q3",
      "question_number": "3",
      "solution_text": "Let P(x) be the statement “x can speak Russian” and let Q(x) be the statement “x knows the computer language C++”. Express each sentence in terms of P(x), Q(x), quantifiers, and logical connectives. The domain consists of all students at your school.",
      "page_start": 1,
      "page_end": 1,
      "subsolutions": [
        {
          "question_id": "q3a",
          "label": "a",
          "answer": "∃x(P(x) ∧ Q(x)).",
          "explanation": null,
          "grading_points": [],
          "points": null,
          "page_start": 1,
          "page_end": 1,
          "source": "same_pdf"
        },
        {
          "question_id": "q3b",
          "label": "b",
          "answer": "∃x(P(x) ∧ ¬Q(x)).",
          "explanation": null,
          "grading_points": [],
          "points": null,
          "page_start": 1,
          "page_end": 1,
          "source": "same_pdf"
        },
        {
          "question_id": "q3c",
          "label": "c",
          "answer": "∀x(P(x) ∨ Q(x)).",
          "explanation": null,
          "grading_points": [],
          "points": null,
          "page_start": 1,
          "page_end": 1,
          "source": "same_pdf"
        },
        {
          "question_id": "q3d",
          "label": "d",
          "answer": "∀x(¬P(x) ∧ ¬Q(x)). Equivalently: ¬∃x(P(x) ∨ Q(x)).",
          "explanation": null,
          "grading_points": [],
          "points": null,
          "page_start": 1,
          "page_end": 1,
          "source": "same_pdf"
        }
      ],
      "warnings": []
    },
    {
      "question_id": "q4",
      "question_number": "4",
      "solution_text": "Determine the truth value of each of these statements if the domain for all variables consists of all integers.",
      "page_start": 2,
      "page_end": 2,
      "subsolutions": [
        {
          "question_id": "q4a",
          "label": "a",
          "answer": "True. The square of every integer is nonnegative.",
          "explanation": null,
          "grading_points": [],
          "points": null,
          "page_start": 2,
          "page_end": 2,
          "source": "same_pdf"
        },
        {
          "question_id": "q4b",
          "label": "b",
          "answer": "False. No integer has square equal to 2.",
          "explanation": null,
          "grading_points": [],
          "points": null,
          "page_start": 2,
          "page_end": 2,
          "source": "same_pdf"
        },
        {
          "question_id": "q4c",
          "label": "c",
          "answer": "True. For every integer n, n² − n = n(n − 1) is nonnegative.",
          "explanation": null,
          "grading_points": [],
          "points": null,
          "page_start": 2,
          "page_end": 2,
          "source": "same_pdf"
        },
        {
          "question_id": "q4d",
          "label": "d",
          "answer": "False. An integer square cannot be negative.",
          "explanation": null,
          "grading_points": [],
          "points": null,
          "page_start": 2,
          "page_end": 2,
          "source": "same_pdf"
        }
      ],
      "warnings": []
    },
    {
      "question_id": "q5",
      "question_number": "5",
      "solution_text": "Express the negation of each of these statements in terms of quantifiers without using the negation symbol.",
      "page_start": 2,
      "page_end": 2,
      "subsolutions": [
        {
          "question_id": "q5a",
          "label": "a",
          "answer": "∃x(x ≤ 1).",
          "explanation": null,
          "grading_points": [],
          "points": null,
          "page_start": 2,
          "page_end": 2,
          "source": "same_pdf"
        },
        {
          "question_id": "q5b",
          "label": "b",
          "answer": "∃x(x > 2).",
          "explanation": null,
          "grading_points": [],
          "points": null,
          "page_start": 2,
          "page_end": 2,
          "source": "same_pdf"
        },
        {
          "question_id": "q5c",
          "label": "c",
          "answer": "∀x(x < 4).",
          "explanation": null,
          "grading_points": [],
          "points": null,
          "page_start": 2,
          "page_end": 2,
          "source": "same_pdf"
        },
        {
          "question_id": "q5d",
          "label": "d",
          "answer": "∀x(x ≥ 0).",
          "explanation": null,
          "grading_points": [],
          "points": null,
          "page_start": 2,
          "page_end": 2,
          "source": "same_pdf"
        },
        {
          "question_id": "q5e",
          "label": "e",
          "answer": "∃x((x ≥ −1) ∧ (x ≤ 2)).",
          "explanation": null,
          "grading_points": [],
          "points": null,
          "page_start": 2,
          "page_end": 2,
          "source": "same_pdf"
        },
        {
          "question_id": "q5f",
          "label": "f",
          "answer": "∀x((x ≥ 4) ∧ (x ≤ 7)).",
          "explanation": null,
          "grading_points": [],
          "points": null,
          "page_start": 2,
          "page_end": 2,
          "source": "same_pdf"
        }
      ],
      "warnings": []
    },
    {
      "question_id": "q6",
      "question_number": "6",
      "solution_text": "Translate these specifications into English, where F(p) is “Printer p is out of service”, B(p) is “Printer p is busy”, L(j) is “Print job j is lost” and Q(j) is “Print job j is queued”.",
      "page_start": 2,
      "page_end": 2,
      "subsolutions": [
        {
          "question_id": "q6a",
          "label": "a",
          "answer": "If there is a printer that is out of service and busy, then there is a print job that is lost.",
          "explanation": null,
          "grading_points": [],
          "points": null,
          "page_start": 2,
          "page_end": 2,
          "source": "same_pdf"
        },
        {
          "question_id": "q6b",
          "label": "b",
          "answer": "If every printer is busy, then there is a print job that is queued.",
          "explanation": null,
          "grading_points": [],
          "points": null,
          "page_start": 2,
          "page_end": 2,
          "source": "same_pdf"
        },
        {
          "question_id": "q6c",
          "label": "c",
          "answer": "If there is a print job that is both queued and lost, then there is a printer that is out of service.",
          "explanation": null,
          "grading_points": [],
          "points": null,
          "page_start": 2,
          "page_end": 2,
          "source": "same_pdf"
        },
        {
          "question_id": "q6d",
          "label": "d",
          "answer": "If every printer is busy and every print job is queued, then there is a print job that is lost.",
          "explanation": null,
          "grading_points": [],
          "points": null,
          "page_start": 2,
          "page_end": 2,
          "source": "same_pdf"
        }
      ],
      "warnings": []
    },
    {
      "question_id": "q7",
      "question_number": "7",
      "solution_text": "As mentioned in the text, the notation ∃!xP(x) denotes “There exists a unique x such that P(x) is true”. If the domain consists of all integers, what are the truth values of these statements?",
      "page_start": 3,
      "page_end": 3,
      "subsolutions": [
        {
          "question_id": "q7a",
          "label": "a",
          "answer": "False. There are many integers greater than 1.",
          "explanation": null,
          "grading_points": [],
          "points": null,
          "page_start": 3,
          "page_end": 3,
          "source": "same_pdf"
        },
        {
          "question_id": "q7b",
          "label": "b",
          "answer": "False. Both x = 1 and x = −1 satisfy x² = 1.",
          "explanation": null,
          "grading_points": [],
          "points": null,
          "page_start": 3,
          "page_end": 3,
          "source": "same_pdf"
        },
        {
          "question_id": "q7c",
          "label": "c",
          "answer": "True. Solving x + 3 = 2x gives the unique integer x = 3.",
          "explanation": null,
          "grading_points": [],
          "points": null,
          "page_start": 3,
          "page_end": 3,
          "source": "same_pdf"
        },
        {
          "question_id": "q7d",
          "label": "d",
          "answer": "False. No integer satisfies x = x + 1.",
          "explanation": null,
          "grading_points": [],
          "points": null,
          "page_start": 3,
          "page_end": 3,
          "source": "same_pdf"
        }
      ],
      "warnings": []
    },
    {
      "question_id": "q8",
      "question_number": "8",
      "solution_text": "Let P(x), Q(x) and R(x) be the statements “x is a professor”, “x is ignorant” and “x is vain”, respectively. Express each of these statements using quantifiers, logical connectives, and P(x), Q(x) and R(x), where the domain consists of all people.",
      "page_start": 3,
      "page_end": 3,
      "subsolutions": [
        {
          "question_id": "q8a",
          "label": "a",
          "answer": "∀x(P(x) → ¬Q(x)). Equivalently: ¬∃x(P(x) ∧ Q(x)).",
          "explanation": null,
          "grading_points": [],
          "points": null,
          "page_start": 3,
          "page_end": 3,
          "source": "same_pdf"
        },
        {
          "question_id": "q8b",
          "label": "b",
          "answer": "∀x(Q(x) → R(x)).",
          "explanation": null,
          "grading_points": [],
          "points": null,
          "page_start": 3,
          "page_end": 3,
          "source": "same_pdf"
        },
        {
          "question_id": "q8c",
          "label": "c",
          "answer": "∀x(P(x) → ¬R(x)).",
          "explanation": null,
          "grading_points": [],
          "points": null,
          "page_start": 3,
          "page_end": 3,
          "source": "same_pdf"
        },
        {
          "question_id": "q8_followup",
          "label": "followup",
          "answer": "No.",
          "explanation": "From (a), professors are not ignorant. From (b), ignorant people are vain. This does not imply that professors are not vain; a professor could be vain without being ignorant.",
          "grading_points": [],
          "points": null,
          "page_start": 3,
          "page_end": 3,
          "source": "same_pdf"
        }
      ],
      "warnings": []
    }
  ],
  "warnings": []
}
